typecats/__about__.py
typecats/__init__.py
typecats/attrs_shim.py
typecats/cats_mypy_plugin.py
typecats/py.typed
typecats/tc.py
typecats/wildcat.py
typecats-1.2.0.dist-info/LICENSE
typecats-1.2.0.dist-info/METADATA
typecats-1.2.0.dist-info/WHEEL
typecats-1.2.0.dist-info/top_level.txt
typecats-1.2.0.dist-info/RECORD
